invarlock/__init__.py
invarlock/__main__.py
invarlock/config.py
invarlock/model_profile.py
invarlock/model_utils.py
invarlock/py.typed
invarlock/security.py
invarlock/sparsity_utils.py
invarlock/_data/runtime/tiers.yaml
invarlock/_data/runtime/profiles/ci_cpu.yaml
invarlock/_data/runtime/profiles/release.yaml
invarlock/adapters/__init__.py
invarlock/adapters/_capabilities.py
invarlock/adapters/auto.py
invarlock/adapters/base.py
invarlock/adapters/base_types.py
invarlock/adapters/capabilities.py
invarlock/adapters/hf_causal.py
invarlock/adapters/hf_causal_onnx.py
invarlock/adapters/hf_loading.py
invarlock/adapters/hf_mixin.py
invarlock/adapters/hf_mlm.py
invarlock/adapters/hf_seq2seq.py
invarlock/adapters/py.typed
invarlock/assurance/__init__.py
invarlock/calibration/__init__.py
invarlock/calibration/spectral_null.py
invarlock/calibration/variance_ve.py
invarlock/cli/__init__.py
invarlock/cli/__main__.py
invarlock/cli/_evidence.py
invarlock/cli/_json.py
invarlock/cli/adapter_auto.py
invarlock/cli/app.py
invarlock/cli/config.py
invarlock/cli/constants.py
invarlock/cli/determinism.py
invarlock/cli/device.py
invarlock/cli/doctor_helpers.py
invarlock/cli/errors.py
invarlock/cli/output.py
invarlock/cli/overhead_utils.py
invarlock/cli/provenance.py
invarlock/cli/utils.py
invarlock/cli/commands/__init__.py
invarlock/cli/commands/calibrate.py
invarlock/cli/commands/certify.py
invarlock/cli/commands/doctor.py
invarlock/cli/commands/explain_gates.py
invarlock/cli/commands/export_html.py
invarlock/cli/commands/plugins.py
invarlock/cli/commands/report.py
invarlock/cli/commands/run.py
invarlock/cli/commands/verify.py
invarlock/core/__init__.py
invarlock/core/abi.py
invarlock/core/api.py
invarlock/core/auto_tuning.py
invarlock/core/bootstrap.py
invarlock/core/checkpoint.py
invarlock/core/contracts.py
invarlock/core/error_utils.py
invarlock/core/events.py
invarlock/core/exceptions.py
invarlock/core/registry.py
invarlock/core/retry.py
invarlock/core/runner.py
invarlock-0.3.7.dist-info/licenses/LICENSE
invarlock-0.3.7.dist-info/METADATA
invarlock-0.3.7.dist-info/WHEEL
invarlock-0.3.7.dist-info/entry_points.txt
invarlock-0.3.7.dist-info/top_level.txt
invarlock-0.3.7.dist-info/RECORD
