Metadata-Version: 2.4
Name: invarlock
Version: 0.3.7
Summary: Edit‑agnostic robustness certificates for weight edits (InvarLock framework)
Author-email: InvarLock Team <oss@invarlock.dev>
Maintainer-email: InvarLock Maintainers <support@invarlock.dev>
License-Expression: Apache-2.0
Project-URL: Homepage, https://github.com/invarlock/invarlock
Project-URL: Repository, https://github.com/invarlock/invarlock
Project-URL: Documentation, https://github.com/invarlock/invarlock/tree/main/docs
Project-URL: Issues, https://github.com/invarlock/invarlock/issues
Project-URL: Changelog, https://github.com/invarlock/invarlock/blob/main/CHANGELOG.md
Keywords: machine-learning,deep-learning,transformers,pytorch,llm,quantization,safety,evaluation,certification
Classifier: Development Status :: 4 - Beta
Classifier: Intended Audience :: Developers
Classifier: Intended Audience :: Science/Research
Classifier: Topic :: Scientific/Engineering :: Artificial Intelligence
Classifier: Programming Language :: Python :: 3
Classifier: Programming Language :: Python :: 3.12
Classifier: Programming Language :: Python :: 3.13
Classifier: Operating System :: OS Independent
Classifier: Typing :: Typed
Requires-Python: >=3.12
License-File: LICENSE
Requires-Dist: typer>=0.15
Requires-Dist: click>=8.1
Requires-Dist: shellingham>=1.5.0
Requires-Dist: pandas>=2.2
Requires-Dist: scikit-learn>=1.4
Requires-Dist: pydantic>=2.0
Requires-Dist: rich>=13.0
Requires-Dist: pyyaml>=6.0
Requires-Dist: markdown>=3.5
Requires-Dist: psutil>=5.9
Requires-Dist: hypothesis>=6.98
Requires-Dist: typing_extensions>=4.7
Requires-Dist: jsonschema>=4.0
Provides-Extra: adapters
Requires-Dist: torch>=2.1.0; extra == "adapters"
Requires-Dist: transformers>=4.53.0; extra == "adapters"
Provides-Extra: hf
Requires-Dist: torch>=2.1.0; extra == "hf"
Requires-Dist: transformers>=4.53.0; extra == "hf"
Requires-Dist: datasets>=3.0; extra == "hf"
Requires-Dist: numpy>=1.24; extra == "hf"
Requires-Dist: huggingface_hub>=0.23; extra == "hf"
Requires-Dist: aiohttp>=3.12.14; extra == "hf"
Requires-Dist: h2>=4.3.0; extra == "hf"
Requires-Dist: pillow>=11.3.0; extra == "hf"
Provides-Extra: guards
Requires-Dist: torch>=2.1.0; extra == "guards"
Requires-Dist: numpy>=1.24; extra == "guards"
Provides-Extra: edits
Requires-Dist: torch>=2.1.0; extra == "edits"
Provides-Extra: eval
Requires-Dist: torch>=2.1.0; extra == "eval"
Requires-Dist: datasets>=3.0; extra == "eval"
Provides-Extra: gptq
Requires-Dist: torch>=2.1.0; extra == "gptq"
Requires-Dist: auto-gptq>=0.7.0; platform_system == "Linux" and extra == "gptq"
Requires-Dist: triton>=2.3.0; platform_system == "Linux" and extra == "gptq"
Requires-Dist: transformers>=4.53.0; extra == "gptq"
Provides-Extra: awq
Requires-Dist: torch>=2.1.0; extra == "awq"
Requires-Dist: autoawq>=0.2.0; platform_system == "Linux" and extra == "awq"
Requires-Dist: transformers>=4.53.0; extra == "awq"
Requires-Dist: triton>=2.3.0; platform_system == "Linux" and extra == "awq"
Provides-Extra: gpu
Requires-Dist: torch>=2.1.0; extra == "gpu"
Requires-Dist: accelerate>=0.27; extra == "gpu"
Requires-Dist: bitsandbytes>=0.41; platform_system == "Linux" and extra == "gpu"
Provides-Extra: all
Requires-Dist: torch>=2.1.0; extra == "all"
Requires-Dist: transformers>=4.53.0; extra == "all"
Requires-Dist: datasets>=3.0; extra == "all"
Requires-Dist: numpy>=1.24; extra == "all"
Requires-Dist: huggingface_hub>=0.23; extra == "all"
Requires-Dist: accelerate>=0.27; extra == "all"
Requires-Dist: bitsandbytes>=0.41; platform_system == "Linux" and extra == "all"
Requires-Dist: auto-gptq>=0.7.0; platform_system == "Linux" and extra == "all"
Requires-Dist: autoawq>=0.2.0; platform_system == "Linux" and extra == "all"
Requires-Dist: triton>=2.3.0; platform_system == "Linux" and extra == "all"
Requires-Dist: aiohttp>=3.12.14; extra == "all"
Requires-Dist: h2>=4.3.0; extra == "all"
Requires-Dist: pillow>=11.3.0; extra == "all"
Provides-Extra: onnx
Requires-Dist: optimum>=1.17.0; extra == "onnx"
Requires-Dist: onnxruntime>=1.17.0; extra == "onnx"
Provides-Extra: dev
Requires-Dist: pytest>=7.0; extra == "dev"
Requires-Dist: pytest-cov>=4.0; extra == "dev"
Requires-Dist: ruff>=0.1.0; extra == "dev"
Requires-Dist: black>=23.0; extra == "dev"
Requires-Dist: mypy>=1.0; extra == "dev"
Requires-Dist: hypothesis>=6.98; extra == "dev"
Requires-Dist: pre-commit>=3.0; extra == "dev"
Requires-Dist: mkdocs>=1.5; extra == "dev"
Requires-Dist: mkdocs-material>=9.5; extra == "dev"
Requires-Dist: mkdocs-mermaid2-plugin>=1.1; extra == "dev"
Requires-Dist: sphinx>=7.0; extra == "dev"
Requires-Dist: matplotlib>=3.7; extra == "dev"
Requires-Dist: bitsandbytes>=0.41; extra == "dev"
Requires-Dist: build>=0.10.0; extra == "dev"
Requires-Dist: twine>=4.0.0; extra == "dev"
Dynamic: license-file
